{
  "project_info": {
    "project_number": "8266811840",
    "project_id": "calendario-47bc3",
    "storage_bucket": "calendario-47bc3.appspot.com"
  },
  "client": [
    {
      "client_info": {
        "mobilesdk_app_id": "1:8266811840:android:78d576fb89fefa1efd2025",
        "android_client_info": {
          "package_name": "com.example.agenda_online"
        }
      },
      "oauth_client": [],
      "api_key": [
        {
          "current_key": "AIzaSyBc4RwpypqXXQjODQj6w1EkSO-lG2CTEOU"
        }
      ],
      "services": {
        "appinvite_service": {
          "other_platform_oauth_client": []
        }
      }
    }
  ],
  "configuration_version": "1"
}